nonebot_plugin_chikari_economy/__init__.py
nonebot_plugin_chikari_economy/data_handles.py
nonebot_plugin_chikari_economy/handles.py
nonebot_plugin_chikari_economy-0.0.7.dist-info/LICENSE
nonebot_plugin_chikari_economy-0.0.7.dist-info/METADATA
nonebot_plugin_chikari_economy-0.0.7.dist-info/WHEEL
nonebot_plugin_chikari_economy-0.0.7.dist-info/top_level.txt
nonebot_plugin_chikari_economy-0.0.7.dist-info/RECORD
