Metadata-Version: 2.1
Name: nonebot_plugin_chikari_economy
Version: 0.0.7
Summary: A economy plugin for nonebot 2
Home-page: https://github.com/mrqx0195/nonebot_plugin_chikari_economy
Author: mrqx0195
Author-email: 2317249571@qq.com
Classifier: Programming Language :: Python :: 3
Classifier: License :: OSI Approved :: MIT License
Classifier: Operating System :: OS Independent
License-File: LICENSE
Requires-Dist: nonebot2 >=2.2.0
Requires-Dist: nonebot-adapter-onebot
Requires-Dist: nonebot-plugin-localstore
